{
    "dozenFirstPercent": {
        "bets": [
            "dozenFirst"
        ],
        "limits": {
            "stopWin": 1,
            "stopLoss": 12
        },
        "progressionCustom": [
            1,
            1,
            2,
            3,
            5,
            7,
            11,
            16,
            24,
            36,
            54,
            90
        ],
        "trigger": {
            "distribution": [
                {
                    "betType": "dozenFirst",
                    "sampleSize": 50,
                    "percentage": 12,
                    "action": "lowerEqual"
                }
            ]
        }
    },
    "dozenSecondPercent": {
        "bets": [
            "dozenSecond"
        ],
        "limits": {
            "stopWin": 1,
            "stopLoss": 12
        },
        "progressionCustom": [
            1,
            1,
            2,
            3,
            5,
            7,
            11,
            16,
            24,
            36,
            54,
            90
        ],
        "trigger": {
            "distribution": [
                {
                    "betType": "dozenSecond",
                    "sampleSize": 50,
                    "percentage": 12,
                    "action": "lowerEqual"
                }
            ]
        }
    },
    "dozenThirdPercent": {
        "bets": [
            "dozenThird"
        ],
        "limits": {
            "stopWin": 1,
            "stopLoss": 12
        },
        "progressionCustom": [
            1,
            1,
            2,
            3,
            5,
            7,
            11,
            16,
            24,
            36,
            54,
            90
        ],
        "trigger": {
            "distribution": [
                {
                    "betType": "dozenThird",
                    "sampleSize": 50,
                    "percentage": 12,
                    "action": "lowerEqual"
                }
            ]
        }
    }
}